perfflowaspect/__init__.py
perfflowaspect/advice_chrome.py
perfflowaspect/advice_dispatch.py
perfflowaspect/aspect.py
perfflowaspect/aspect_base.py
perfflowaspect-0.1.0.dist-info/METADATA
perfflowaspect-0.1.0.dist-info/WHEEL
perfflowaspect-0.1.0.dist-info/top_level.txt
perfflowaspect-0.1.0.dist-info/RECORD
