Metadata-Version: 2.1
Name: perfflowaspect
Version: 0.1.0
Summary: tool to analyze cross-cutting performance concerns of composite scientific workflows.
Home-page: https://github.com/flux-framework/PerfFlowAspect
Author: Tapasya Patki, Stephanie Brink
Author-email: patki1@llnl.gov, brink2@llnl.gov
License: UNKNOWN
Project-URL: Source Code, https://github.com/flux-framework/PerfFlowAspect
Project-URL: Documentation, https://perfflowaspect.readthedocs.io/en/latest/
Platform: UNKNOWN
Classifier: Intended Audience :: Developers
Classifier: Intended Audience :: Science/Research
Classifier: Topic :: Scientific/Engineering
Classifier: Topic :: System :: Distributed Computing
Classifier: Programming Language :: Python :: 3
Classifier: Programming Language :: Python :: 3.8
Classifier: Programming Language :: Python :: 3.9
Requires-Python: >=3.8
Requires-Dist: psutil
